flask_production/__init__.py
flask_production/_capture.py
flask_production/core.py
flask_production/hols.py
flask_production/jobs.py
flask_production/print_logger.py
flask_production/sched.py
flask_production/script_func.py
flask_production/plugins/__init__.py
flask_production/plugins/ctrl_panel.py
flask_production/plugins/html_templates.py
flask_production/plugins/task_monitor.py
flask_production/plugins/web/index.html
flask_production/plugins/web/css/ctrl_panel.css
flask_production/plugins/web/css/dark_theme.css
flask_production/plugins/web/css/taskmonitor.css
flask_production/plugins/web/ico/flask_boiler.ico
flask_production/plugins/web/js/ctrl_panel.js
flask_production/plugins/web/js/task.js
flask_production/plugins/web/js/taskmonitor.js
flask_production/state/__init__.py
flask_production/state/base.py
flask_production/state/db.py
flask_production/state/fs.py
flask_production-3.1.8.dist-info/licenses/LICENSE
flask_production-3.1.8.dist-info/METADATA
flask_production-3.1.8.dist-info/WHEEL
flask_production-3.1.8.dist-info/top_level.txt
flask_production-3.1.8.dist-info/RECORD
