Metadata-Version: 2.4
Name: flask_production
Version: 3.1.8
Summary: cherrypy server for Flask + task scheduler and monitor
Home-page: https://github.com/shashfrankenstien/Flask_Production
Author: Shashank Gopikrishna
Author-email: shashank.gopikrishna@gmail.com
License: MIT
License-File: LICENSE
Requires-Dist: flask
Requires-Dist: CherryPy
Requires-Dist: holidays<1.0
Requires-Dist: MonthDelta
Requires-Dist: psutil
Requires-Dist: python_dateutil
Requires-Dist: requests
Dynamic: license-file
